flask_router_wrapper/__init__.py
flask_router_wrapper/exception.py
flask_router_wrapper/middleware.py
flask_router_wrapper/router.py
flask_router_wrapper/version.py
Flask_Router_Wrapper-0.1.2.dist-info/LICENSE
Flask_Router_Wrapper-0.1.2.dist-info/METADATA
Flask_Router_Wrapper-0.1.2.dist-info/WHEEL
Flask_Router_Wrapper-0.1.2.dist-info/top_level.txt
Flask_Router_Wrapper-0.1.2.dist-info/RECORD
