Metadata-Version: 2.1
Name: Flask-Router-Wrapper
Version: 0.1.2
Summary: A Flask extension which wraps flask application router
Home-page: https://github.com/josephsalimin/flask-router-wrapper
License: MIT
Platform: UNKNOWN
Requires-Python: >=3.6.*
Requires-Dist: Flask (>=1.1.2)
